createnv/__init__.py
createnv/cli.py
createnv/config.py
createnv/echo.py
createnv/generator.py
createnv/parser.py
createnv-0.0.2.dist-info/entry_points.txt
createnv-0.0.2.dist-info/LICENSE
createnv-0.0.2.dist-info/WHEEL
createnv-0.0.2.dist-info/METADATA
createnv-0.0.2.dist-info/RECORD
